XwPyAutorg/XwPyAutorg.py
XwPyAutorg/__init__.py
XwPyAutorg/setup.py
XwPyAutorg-1.0.dist-info/METADATA
XwPyAutorg-1.0.dist-info/WHEEL
XwPyAutorg-1.0.dist-info/license.txt
XwPyAutorg-1.0.dist-info/top_level.txt
XwPyAutorg-1.0.dist-info/RECORD
