Metadata-Version: 2.1
Name: XwPyAutorg
Version: 1.0
Summary: ...[非常NB]反正
Author: xiaowang
Author-email: wzxddzyj1@outlook.com
License-File: license.txt
